conscia/secretvalue/__init__.py
conscia/secretvalue/click_param.py
conscia/secretvalue/py.typed
conscia_secretvalue-0.2.5.1.dist-info/METADATA
conscia_secretvalue-0.2.5.1.dist-info/WHEEL
conscia_secretvalue-0.2.5.1.dist-info/RECORD
